oc_config_validate/__init__.py
oc_config_validate/__main__.py
oc_config_validate/context.py
oc_config_validate/formatter.py
oc_config_validate/poc.py
oc_config_validate/runner.py
oc_config_validate/schema.py
oc_config_validate/target.py
oc_config_validate/testbase.py
oc_config_validate/gnmi/__init__.py
oc_config_validate/gnmi/gnmi_ext_pb2.py
oc_config_validate/gnmi/gnmi_ext_pb2_grpc.py
oc_config_validate/gnmi/gnmi_pb2.py
oc_config_validate/gnmi/gnmi_pb2_grpc.py
oc_config_validate/models/__init__.py
oc_config_validate/models/acl.py
oc_config_validate/models/aft.py
oc_config_validate/models/ate.py
oc_config_validate/models/bgp.py
oc_config_validate/models/catalog.py
oc_config_validate/models/defined_sets.py
oc_config_validate/models/devices_manifest.py
oc_config_validate/models/extensions.py
oc_config_validate/models/firewall.py
oc_config_validate/models/gribi.py
oc_config_validate/models/interfaces.py
oc_config_validate/models/isis.py
oc_config_validate/models/keychain.py
oc_config_validate/models/lacp.py
oc_config_validate/models/lldp.py
oc_config_validate/models/local_routing.py
oc_config_validate/models/macsec.py
oc_config_validate/models/mpls.py
oc_config_validate/models/multicast.py
oc_config_validate/models/network_instance.py
oc_config_validate/models/openflow.py
oc_config_validate/models/optical_transport.py
oc_config_validate/models/ospf.py
oc_config_validate/models/p4rt.py
oc_config_validate/models/pcep.py
oc_config_validate/models/platform.py
oc_config_validate/models/policy.py
oc_config_validate/models/policy_forwarding.py
oc_config_validate/models/probes.py
oc_config_validate/models/qos.py
oc_config_validate/models/relay_agent.py
oc_config_validate/models/rib.py
oc_config_validate/models/sampling.py
oc_config_validate/models/segment_routing.py
oc_config_validate/models/stp.py
oc_config_validate/models/system.py
oc_config_validate/models/telemetry.py
oc_config_validate/models/types.py
oc_config_validate/models/vlan.py
oc_config_validate/models/wifi.py
oc_config_validate-1000.0.2.dist-info/METADATA
oc_config_validate-1000.0.2.dist-info/WHEEL
oc_config_validate-1000.0.2.dist-info/top_level.txt
oc_config_validate-1000.0.2.dist-info/RECORD
